tcconfig/__init__.py
tcconfig/__version__.py
tcconfig/_argparse_wrapper.py
tcconfig/_capabilities.py
tcconfig/_command.py
tcconfig/_common.py
tcconfig/_const.py
tcconfig/_docker.py
tcconfig/_error.py
tcconfig/_importer.py
tcconfig/_iptables.py
tcconfig/_logger.py
tcconfig/_main.py
tcconfig/_netem_param.py
tcconfig/_network.py
tcconfig/_shaping_rule_finder.py
tcconfig/_split_line_list.py
tcconfig/_tc_command_helper.py
tcconfig/_tc_script.py
tcconfig/tcdel.py
tcconfig/tcset.py
tcconfig/tcshow.py
tcconfig/traffic_control.py
tcconfig/parser/__init__.py
tcconfig/parser/_class.py
tcconfig/parser/_filter.py
tcconfig/parser/_interface.py
tcconfig/parser/_model.py
tcconfig/parser/_qdisc.py
tcconfig/parser/shaping_rule.py
tcconfig/shaper/__init__.py
tcconfig/shaper/_interface.py
tcconfig/shaper/htb.py
tcconfig/shaper/tbf.py
tcconfig-0.30.0.dist-info/licenses/LICENSE
tcconfig-0.30.0.dist-info/METADATA
tcconfig-0.30.0.dist-info/WHEEL
tcconfig-0.30.0.dist-info/entry_points.txt
tcconfig-0.30.0.dist-info/top_level.txt
tcconfig-0.30.0.dist-info/RECORD
