Metadata-Version: 2.4
Name: tcconfig
Version: 0.30.0
Summary: tcconfig is a tc command wrapper. Make it easy to set up traffic control of network bandwidth/latency/packet-loss/packet-corruption/etc. to a network-interface/Docker-container(veth).
Home-page: https://github.com/thombashi/tcconfig
Author: Tsuyoshi Hombashi
Author-email: tsuyoshi.hombashi@gmail.com
License: MIT License
Project-URL: Changelog, https://github.com/thombashi/tcconfig/blob/master/CHANGELOG.md
Project-URL: Documentation, https://tcconfig.rtfd.io/
Project-URL: Source, https://github.com/thombashi/tcconfig
Project-URL: Tracker, https://github.com/thombashi/tcconfig/issues
Keywords: network,traffic control,tc,traffic shaping,docker
Classifier: Development Status :: 4 - Beta
Classifier: Environment :: Console
Classifier: Intended Audience :: Developers
Classifier: Intended Audience :: Information Technology
Classifier: Intended Audience :: System Administrators
Classifier: Intended Audience :: Telecommunications Industry
Classifier: License :: OSI Approved :: MIT License
Classifier: Operating System :: POSIX
Classifier: Operating System :: POSIX :: Linux
Classifier: Programming Language :: Python :: 3
Classifier: Programming Language :: Python :: 3.9
Classifier: Programming Language :: Python :: 3.10
Classifier: Programming Language :: Python :: 3.11
Classifier: Programming Language :: Python :: 3.12
Classifier: Programming Language :: Python :: 3.13
Classifier: Topic :: System :: Operating System Kernels :: Linux
Classifier: Topic :: System :: Networking
Classifier: Topic :: System :: Systems Administration
Classifier: Topic :: Software Development :: Testing
Requires-Python: >=3.9
License-File: LICENSE
Requires-Dist: DataProperty<2,>=1.0.2
Requires-Dist: docker<8,>=1.9.0
Requires-Dist: humanreadable<1,>=0.3
Requires-Dist: loguru<1,>=0.4.1
Requires-Dist: msgfy<1,>=0.1.0
Requires-Dist: path<18,>=13
Requires-Dist: pyparsing<4,>=2.0.3
Requires-Dist: pyroute2<1,>=0.6.1
Requires-Dist: SimpleSQLite!=1.5.0,!=1.5.1,<2,>=1.3.2
Requires-Dist: subprocrunner<3,>=1.2.1
Requires-Dist: typepy<2,>=1.1.1
Requires-Dist: voluptuous<1
Provides-Extra: all
Requires-Dist: Pygments<3,>=2.2.0; extra == "all"
Provides-Extra: buildexe
Requires-Dist: pyinstaller<7,>=4.7; extra == "buildexe"
Provides-Extra: color
Requires-Dist: Pygments<3,>=2.2.0; extra == "color"
Provides-Extra: docs
Requires-Dist: sphinx_rtd_theme>=1.2.2; extra == "docs"
Requires-Dist: Sphinx>=2.4; extra == "docs"
Provides-Extra: test
Requires-Dist: allpairspy>=2.5; extra == "test"
Requires-Dist: pingparsing>=1; extra == "test"
Requires-Dist: pytest>=6.0.1; extra == "test"
Requires-Dist: pytest-discord>=0.1.6; extra == "test"
Requires-Dist: pytest-md-report>=0.6.2; extra == "test"
Dynamic: author
Dynamic: author-email
Dynamic: classifier
Dynamic: description
Dynamic: description-content-type
Dynamic: home-page
Dynamic: keywords
Dynamic: license
Dynamic: license-file
Dynamic: project-url
Dynamic: provides-extra
Dynamic: requires-dist
Dynamic: requires-python
Dynamic: summary
